windlib.py
windlib-1.9.3.dist-info/LICENSE
windlib-1.9.3.dist-info/METADATA
windlib-1.9.3.dist-info/WHEEL
windlib-1.9.3.dist-info/top_level.txt
windlib-1.9.3.dist-info/RECORD
