Metadata-Version: 2.1
Name: windlib
Version: 1.9.3
Summary: A useful functions library for everyone.
Home-page: https://gitee.com/SNWCreations/windlib
Author: SNWCreations
Author-email: snwcreations@qq.com
License: MIT License
Project-URL: Bug Tracker, https://gitee.com/SNWCreations/windlib/issues
Platform: UNKNOWN
Classifier: Development Status :: 5 - Production/Stable
Classifier: Intended Audience :: Developers
Classifier: Programming Language :: Python :: 3 :: Only
Classifier: License :: OSI Approved :: MIT License
Classifier: Topic :: Software Development :: Libraries :: Python Modules
Requires-Dist: requests
Requires-Dist: rarfile
